{
  "category": "miscellaneous",
  "created_date": "2025-09-15T22:48:58.435037",
  "default_ports": [
    10,
    20,
    80,
    443,
    3000,
    3001,
    3002,
    5432,
    6379,
    27017
  ],
  "dependencies": [],
  "description": "JavaScript runtime built on Chrome's V8 JavaScript engine. Essential platform for modern web applications, APIs, and microservices with enterprise-grade performance and security features.",
  "difficulty_level": "intermediate",
  "documentation_url": "https://howtomgr.github.io/miscellaneous/nodejs",
  "estimated_setup_time": "15-30 minutes",
  "features": [
    "multi-os-support",
    "comprehensive-documentation",
    "security-hardening",
    "performance-optimization",
    "backup-restore-procedures",
    "troubleshooting-guides"
  ],
  "guide_path": "/miscellaneous/nodejs",
  "installation_methods": [
    "native-packages",
    "source-compilation"
  ],
  "last_updated": "2025-09-15T22:48:58.435054",
  "license": "Open Source",
  "maintenance_status": "active",
  "name": "nodejs",
  "repository_url": "https://github.com/howtomgr/nodejs",
  "spec_version": "2.0",
  "subcategory": "miscellaneous",
  "supported_os": [
    "rhel",
    "centos",
    "rocky",
    "almalinux",
    "arch"
  ],
  "tags": [
    "miscellaneous",
    "containerization",
    "observability",
    "data-storage",
    "networking",
    "security",
    "data-protection",
    "communication"
  ],
  "title": "Node.js Installation Guide",
  "version": "1.0.0",
  "website_url": "https://howtomgr.github.io/miscellaneous/nodejs"
}